stupidwallet/__init__.py
stupidwallet/classes/__init__.py
stupidwallet/classes/_wallet.py
stupidwallet-0.1.16.dist-info/LICENSE
stupidwallet-0.1.16.dist-info/METADATA
stupidwallet-0.1.16.dist-info/WHEEL
stupidwallet-0.1.16.dist-info/RECORD
