Metadata-Version: 2.1
Name: stupidwallet
Version: 0.1.16
Summary: The package which use StupidWallet API
License: GNU GPLv3
Author: Alekzum
Author-email: 68947902+Alekzum@users.noreply.github.com
Requires-Python: >=3.11,<4.0
Classifier: License :: Other/Proprietary License
Classifier: Programming Language :: Python :: 3
Classifier: Programming Language :: Python :: 3.11
Classifier: Programming Language :: Python :: 3.12
Requires-Dist: httpx (>=0.27.0,<0.28.0)
